pixcdust/__init__.py
pixcdust/converters/__init__.py
pixcdust/converters/core.py
pixcdust/converters/geo_utils.py
pixcdust/converters/gpkg.py
pixcdust/converters/parquet.py
pixcdust/converters/shapefile.py
pixcdust/converters/zarr.py
pixcdust/dggs/__init__.py
pixcdust/dggs/dggs_converter.py
pixcdust/dggs/h3_tools.py
pixcdust/downloaders/__init__.py
pixcdust/downloaders/hydroweb_next.py
pixcdust/notebooks/convert/convert_to_zcollection.ipynb
pixcdust/notebooks/convert/dggs_tuto.ipynb
pixcdust/notebooks/convert/download_pixc_to_gpkg.ipynb
pixcdust/notebooks/convert/download_pixc_to_zarr.ipynb
pixcdust/notebooks/data/aoi.gpkg
pixcdust/notebooks/data/h3_gpkg.gpkg
pixcdust/notebooks/read_and_use/read_netcdf.ipynb
pixcdust/readers/__init__.py
pixcdust/readers/base_reader.py
pixcdust/readers/gpkg.py
pixcdust/readers/netcdf.py
pixcdust/readers/zarr.py
pixcdust/tests/__init__.py
pixcdust/tests/conftest.py
pixcdust/tests/init_tests.py
pixcdust/tests/mock.py
pixcdust/tests/mock_data/swot_pixc.nc
pixcdust/tests/test_converters.py
pixcdust/tests/test_converters_mock.py
pixcdust/tests/test_dggs.py
pixcdust/tests/test_downloaders.py
pixcdust/tools/convert_pixc.py
pixcdust-0.1.2.dist-info/LICENSE.md
pixcdust-0.1.2.dist-info/METADATA
pixcdust-0.1.2.dist-info/WHEEL
pixcdust-0.1.2.dist-info/RECORD
