Metadata-Version: 2.1
Name: pixcdust
Version: 0.1.2
Summary: 
Author: zawadzl
Author-email: lionel.zawadzki@cnes.fr
Requires-Python: >=3.10,<4.0
Classifier: Programming Language :: Python :: 3
Classifier: Programming Language :: Python :: 3.10
Classifier: Programming Language :: Python :: 3.11
Requires-Dist: astropy (>=6.1.7,<7.0.0)
Requires-Dist: astropy-healpix (>=1.1.0,<2.0.0)
Requires-Dist: black (>=24.2.0,<25.0.0)
Requires-Dist: branca (>=0.7.2,<0.8.0)
Requires-Dist: click (>=8.1.7,<9.0.0)
Requires-Dist: eodag (>=2.12.1,<3.0.0)
Requires-Dist: fiona (>=1.9.5,<2.0.0)
Requires-Dist: flake8 (>=7.0.0,<8.0.0)
Requires-Dist: folium (>=0.16.0,<0.17.0)
Requires-Dist: geopandas (>=0.14.3,<0.15.0)
Requires-Dist: h3 (>=3.7.6,<4.0.0)
Requires-Dist: netcdf4 (>=1.6.5,<2.0.0)
Requires-Dist: numpy (>=1.26.4,<2.0.0)
Requires-Dist: pandas (>=2.2.0,<3.0.0)
Requires-Dist: pyarrow (>=16.1.0,<17.0.0)
Requires-Dist: pyogrio (>=0.8.0,<0.9.0)
Requires-Dist: scipy (>=1.8.0,<2.0.0)
Requires-Dist: shapely (>=2.0.3,<3.0.0)
Requires-Dist: tqdm (>=4.66.4,<5.0.0)
Requires-Dist: xarray (>=2024.2.0,<2025.0.0)
Requires-Dist: xdggs (>=0.2.0,<0.3.0)
Requires-Dist: xvec (>=0.3.0,<0.4.0)
Requires-Dist: zarr (>=2.11,<3.0)
Requires-Dist: zcollection (>=2024.2.0,<2025.0.0)
